README.md
setup.py
chromedrivermutual_update.egg-info/PKG-INFO
chromedrivermutual_update.egg-info/SOURCES.txt
chromedrivermutual_update.egg-info/dependency_links.txt
chromedrivermutual_update.egg-info/requires.txt
chromedrivermutual_update.egg-info/top_level.txt
update_chrome/__init__.py
update_chrome/core.py