Metadata-Version: 2.1
Name: chromedrivermutual-update
Version: 0.0.5
Summary: Update automatic for automations python, when your path, takes your chrome version and update 
Home-page: UNKNOWN
Author: Thiago Graça
Author-email: thiago448@gmail.com
License: MIT License
Keywords: chromedriver update,selenium,chromedriver
Platform: UNKNOWN
